examples/__init__.py
examples/movies/__init__.py
examples/movies/interpret.py
examples/movies/comparators/__init__.py
examples/movies/comparators/dimension/__init__.py
examples/movies/comparators/dimension/titles.py
examples/movies/comparators/dimension/years.py
examples/movies/comparators/entity/__init__.py
examples/movies/comparators/entity/avwork.py
examples/movies/entities/__init__.py
examples/movies/entities/avwork.py
mucho/__init__.py
mucho/comparison/__init__.py
mucho/comparison/comparator/__init__.py
mucho/comparison/comparator/dimension/__init__.py
mucho/comparison/comparator/dimension/dimension.py
mucho/comparison/comparator/dimension/meta.py
mucho/comparison/comparator/dimension/property.py
mucho/comparison/comparator/entity/__init__.py
mucho/comparison/comparator/entity/entity.py
mucho/comparison/comparator/entity/meta.py
mucho/comparison/result/__init__.py
mucho/comparison/result/result.py
mucho/dsl/__init__.py
mucho/dsl/compiler/__init__.py
mucho/dsl/compiler/compiler.py
mucho/dsl/compiler/grammar/rules.lrk
mucho/dsl/compiler/transformer/__init__.py
mucho/dsl/compiler/transformer/transformer.py
mucho/dsl/compiler/transformer/model/__init__.py
mucho/dsl/compiler/transformer/model/condition.py
mucho/dsl/compiler/transformer/model/operator.py
mucho/dsl/compiler/transformer/model/rule.py
mucho/dsl/compiler/transformer/model/value.py
mucho/dsl/compiler/transformer/model/variable.py
mucho/dsl/virtualmachine/__init__.py
mucho/dsl/virtualmachine/virtualmachine.py
tests/__init__.py
tests/comparison/__init__.py
tests/comparison/comparator/__init__.py
tests/comparison/comparator/test_entity.py
tests/dsl/__init__.py
tests/dsl/test_integration.py
tests/dsl/compiler/__init__.py
tests/dsl/compiler/grammar/__init__.py
tests/dsl/compiler/grammar/test_grammar.py
tests/dsl/compiler/transformer/__init__.py
tests/dsl/compiler/transformer/test_transformer.py
tests/dsl/compiler/transformer/model/__init__.py
tests/dsl/compiler/transformer/model/test_condition.py
mucho-0.2.1.dist-info/LICENSE.txt
mucho-0.2.1.dist-info/METADATA
mucho-0.2.1.dist-info/WHEEL
mucho-0.2.1.dist-info/top_level.txt
mucho-0.2.1.dist-info/RECORD
